[
  {
    "levelId": "Level 1: Animals (Ẹranko) — speaker2",
    "category": "themed",
    "validSpeakers": [
      "speaker2"
    ],
    "words": [
      "aja_dog",
      "eye_bird",
      "ejo_snake",
      "esin_horse",
      "pepeye_duck"
    ]
  },
  {
    "levelId": "Level 2: The Home & Objects (Nǹkan Ilé) — speaker2",
    "category": "themed",
    "validSpeakers": [
      "speaker2"
    ],
    "words": [
      "aso_cloth",
      "baluwe_bathroom",
      "ibusun_bed",
      "ilekun_door"
    ]
  },
  {
    "levelId": "Level 2: The Home & Objects (Nǹkan Ilé) — speaker3",
    "category": "themed",
    "validSpeakers": [
      "speaker3"
    ],
    "words": [
      "aso_cloth",
      "ose_soap",
      "ibusun_bed"
    ]
  },
  {
    "levelId": "Level 3: Body Parts (Ẹ̀yà Ara) — speaker1",
    "category": "themed",
    "validSpeakers": [
      "speaker1"
    ],
    "words": [
      "ori_head",
      "oju_eye",
      "imu_nose",
      "eti_ear",
      "enu_mouth",
      "orun_neck",
      "owo_hand",
      "ikun_stomach",
      "ejika_shoulder"
    ]
  },
  {
    "levelId": "Level 4: Body Parts 2 (Ẹ̀yà Ara) — speaker2",
    "category": "themed",
    "validSpeakers": [
      "speaker2"
    ],
    "words": [
      "itan_thigh",
      "aya_chest",
      "ete_lip",
      "eyin_back",
      "idodo_navel",
      "eekanna_nail"
    ]
  },
  {
    "levelId": "Level 5: Action Words (Ọ̀rọ̀ Ìṣe) — speaker2",
    "category": "themed",
    "validSpeakers": [
      "speaker2"
    ],
    "words": [
      "lo_go",
      "ra_crawl",
      "wa_come",
      "dide_stand",
      "jeun_eat",
      "sare_run",
      "irin_walk"
    ]
  },
  {
    "levelId": "Level 6: Nature & Environment (Àyíká) — speaker2",
    "category": "themed",
    "validSpeakers": [
      "speaker2"
    ],
    "words": [
      "ewe_leaf",
      "igbo_forest",
      "eye_bird",
      "ejo_snake",
      "ojo_day"
    ]
  },
  {
    "levelId": "Level 7: Everyday Life & Food (Ìgbésí Ayé) — speaker2",
    "category": "themed",
    "validSpeakers": [
      "speaker2"
    ],
    "words": [
      "pele_sorry",
      "jeun_eat",
      "ewa_beans",
      "ewa_beauty"
    ]
  },
  {
    "levelId": "Level 8: Time & Months (Àkókò àti Oṣù) — speaker2",
    "category": "themed",
    "validSpeakers": [
      "speaker2"
    ],
    "words": [
      "ojo_day",
      "igbe_april",
      "ogun_august",
      "ope_december",
      "seere_january",
      "erele_february",
      "ebibi_may",
      "okudu_june",
      "agemo_july",
      "owewe_september",
      "owawa_october",
      "beelu_november"
    ]
  },
  {
    "levelId": "Syllable Practice 1 — speaker1",
    "category": "syllable_reinforcement",
    "validSpeakers": [
      "speaker1"
    ],
    "words": [
      "awo_plate",
      "enu_mouth",
      "eti_ear",
      "ikun_stomach",
      "imu_nose",
      "oju_eye",
      "ori_head",
      "orun_neck",
      "owo_hand",
      "ejika_shoulder"
    ]
  },
  {
    "levelId": "Syllable Practice 1 — speaker2",
    "category": "syllable_reinforcement",
    "validSpeakers": [
      "speaker2"
    ],
    "words": [
      "lo_go",
      "ra_crawl",
      "wa_come",
      "aja_dog",
      "aso_cloth",
      "aya_chest",
      "dide_stand",
      "ejo_snake",
      "ewe_leaf",
      "agemo_july"
    ]
  },
  {
    "levelId": "Syllable Practice 2 — speaker2",
    "category": "syllable_reinforcement",
    "validSpeakers": [
      "speaker2"
    ],
    "words": [
      "esin_horse",
      "ewa_beauty",
      "ewa_beans",
      "ete_lip",
      "eye_bird",
      "ope_december",
      "eyin_back",
      "owawa_october",
      "ebibi_may",
      "erele_february"
    ]
  },
  {
    "levelId": "Syllable Practice 3 — speaker2",
    "category": "syllable_reinforcement",
    "validSpeakers": [
      "speaker2"
    ],
    "words": [
      "igbe_april",
      "igbo_forest",
      "irin_iron",
      "itan_thigh",
      "irin_walk",
      "jeun_eat",
      "ogun_august",
      "ibusun_bed",
      "idodo_navel",
      "ilekun_door"
    ]
  },
  {
    "levelId": "Syllable Practice 4 — speaker2",
    "category": "syllable_reinforcement",
    "validSpeakers": [
      "speaker2"
    ],
    "words": [
      "ojo_day",
      "oju_eye",
      "pele_sorry",
      "sare_run",
      "okudu_june",
      "owewe_september",
      "baluwe_bathroom",
      "beelu_november",
      "pepeye_duck",
      "eekanna_nail"
    ]
  },
  {
    "levelId": "Syllable Practice 1 — speaker3",
    "category": "syllable_reinforcement",
    "validSpeakers": [
      "speaker3"
    ],
    "words": [
      "aso_cloth",
      "ese_leg",
      "ose_soap",
      "ibusun_bed",
      "ikoko_pot"
    ]
  },
  {
    "levelId": "Tone Pattern (mid-high) — speaker1",
    "category": "tone_pattern",
    "validSpeakers": [
      "speaker1"
    ],
    "words": [
      "eti_ear",
      "imu_nose",
      "oju_eye",
      "ori_head"
    ]
  },
  {
    "levelId": "Tone Pattern (mid-high) — speaker2",
    "category": "tone_pattern",
    "validSpeakers": [
      "speaker2"
    ],
    "words": [
      "aja_dog",
      "ewe_leaf",
      "igbo_forest",
      "ojo_day",
      "oju_eye"
    ]
  },
  {
    "levelId": "Tone Pattern (mid-mid) — speaker2",
    "category": "tone_pattern",
    "validSpeakers": [
      "speaker2"
    ],
    "words": [
      "aso_cloth",
      "esin_horse",
      "eye_bird",
      "igbe_april",
      "irin_iron",
      "itan_thigh",
      "jeun_eat"
    ]
  },
  {
    "levelId": "Tone Pattern (low-low) — speaker2",
    "category": "tone_pattern",
    "validSpeakers": [
      "speaker2"
    ],
    "words": [
      "aya_chest",
      "ete_lip",
      "ewa_beans",
      "eyin_back",
      "irin_walk"
    ]
  },
  {
    "levelId": "Endless Practice 1 — speaker1",
    "category": "endless_practice",
    "validSpeakers": [
      "speaker1"
    ],
    "words": [
      "awo_plate",
      "ori_head",
      "ikun_stomach",
      "orun_neck",
      "ikoko_pot",
      "ejika_shoulder",
      "enu_mouth",
      "owo_hand"
    ]
  },
  {
    "levelId": "Endless Practice 2 — speaker1",
    "category": "endless_practice",
    "validSpeakers": [
      "speaker1"
    ],
    "words": [
      "owo_hand",
      "ikoko_pot",
      "orun_neck",
      "awo_plate",
      "imu_nose",
      "ejika_shoulder",
      "eti_ear",
      "ori_head"
    ]
  },
  {
    "levelId": "Endless Practice 3 — speaker1",
    "category": "endless_practice",
    "validSpeakers": [
      "speaker1"
    ],
    "words": [
      "imu_nose",
      "eti_ear",
      "ori_head",
      "ikoko_pot",
      "awo_plate",
      "ikun_stomach",
      "owo_hand",
      "oju_eye"
    ]
  },
  {
    "levelId": "Endless Practice 1 — speaker2",
    "category": "endless_practice",
    "validSpeakers": [
      "speaker2"
    ],
    "words": [
      "irin_walk",
      "beelu_november",
      "baluwe_bathroom",
      "igbe_april",
      "owawa_october",
      "idodo_navel",
      "sare_run",
      "ewa_beans"
    ]
  },
  {
    "levelId": "Endless Practice 2 — speaker2",
    "category": "endless_practice",
    "validSpeakers": [
      "speaker2"
    ],
    "words": [
      "ogun_august",
      "oju_eye",
      "ope_december",
      "ewe_leaf",
      "ra_crawl",
      "ewa_beans",
      "igbo_forest",
      "aja_dog"
    ]
  },
  {
    "levelId": "Endless Practice 3 — speaker2",
    "category": "endless_practice",
    "validSpeakers": [
      "speaker2"
    ],
    "words": [
      "seere_january",
      "irin_iron",
      "igbe_april",
      "idodo_navel",
      "igbo_forest",
      "owewe_september",
      "okudu_june",
      "agemo_july"
    ]
  },
  {
    "levelId": "Endless Practice 1 — speaker3",
    "category": "endless_practice",
    "validSpeakers": [
      "speaker3"
    ],
    "words": [
      "aso_cloth",
      "ikoko_pot",
      "ibusun_bed",
      "ese_leg",
      "ose_soap"
    ]
  },
  {
    "levelId": "Endless Practice 2 — speaker3",
    "category": "endless_practice",
    "validSpeakers": [
      "speaker3"
    ],
    "words": [
      "ese_leg",
      "aso_cloth",
      "ibusun_bed",
      "ikoko_pot",
      "ose_soap"
    ]
  },
  {
    "levelId": "Endless Practice 3 — speaker3",
    "category": "endless_practice",
    "validSpeakers": [
      "speaker3"
    ],
    "words": [
      "ose_soap",
      "ese_leg",
      "ibusun_bed",
      "aso_cloth",
      "ikoko_pot"
    ]
  }
]